CHANGES.rst
MANIFEST.in
README.rst
setup.py
pyramid_scss/__init__.py
pyramid_scss/controller.py
pyramid_scss.egg-info/PKG-INFO
pyramid_scss.egg-info/SOURCES.txt
pyramid_scss.egg-info/dependency_links.txt
pyramid_scss.egg-info/not-zip-safe
pyramid_scss.egg-info/requires.txt
pyramid_scss.egg-info/top_level.txt
pyramid_scss/tests/fixtures/test.css
pyramid_scss/tests/fixtures/test_compress.css
pyramid_scss/tests/fixtures/test_nocompress.css