Metadata-Version: 1.1
Name: pyramid-scss
Version: 0.4
Summary: Adds support for SCSS to Pyramid projects
Home-page: https://github.com/jessedhillon/pyramid_scss
Author: Jesse Dhillon
Author-email: jesse@deva0.net
License: UNKNOWN
Keywords: web wsgi css scss pyramid
Platform: UNKNOWN
Classifier: Programming Language :: Python
Classifier: Framework :: Pylons
Classifier: Topic :: Internet :: WWW/HTTP
Classifier: Topic :: Internet :: WWW/HTTP :: WSGI :: Application
Classifier: Topic :: Software Development :: Code Generators
